{
	"m_Version": 12,
	"DisplayName": "USBs",
	"Icon": "Radio",
	"Color": "FBFCFEFF",
	"IsExchange": 0,
	"InitStockPercent": 100.0,
	"Items": [
		{
			"ClassName": "USB_Mo3boosie",
			"MaxPriceThreshold": 250,
			"MinPriceThreshold": 250,
			"SellPricePercent": 100,
			"MaxStockThreshold": 3,
			"MinStockThreshold": 1,
			"QuantityPercent": -1,
			"SpawnAttachments": [],
			"Variants": [
				"USB_WeezyDreams",
				"USB_SuicideBoys",
				"USB_VaporsPlaylist"
			]
		},
		{
			"ClassName": "Playlist_Bolbi",
			"MaxPriceThreshold": 500,
			"MinPriceThreshold": 500,
			"SellPricePercent": 100,
			"MaxStockThreshold": 3,
			"MinStockThreshold": 1,
			"QuantityPercent": -1,
			"SpawnAttachments": [],
			"Variants": []
		},
		{
			"ClassName": "USB_ArcticMonkeys_DoIWannaKnow",
			"MaxPriceThreshold": 250,
			"MinPriceThreshold": 250,
			"SellPricePercent": 100,
			"MaxStockThreshold": 3,
			"MinStockThreshold": 1,
			"QuantityPercent": -1,
			"SpawnAttachments": [],
			"Variants": [
				"USB_AronChupaAndLittleSisNora_RaveInTheGrave",
				"USB_Bakermat_LearnToLose",
				"USB_BombsAway_DrunkArcade",
				"USB_CamilaCabello_Havana",
				"USB_ConnorPrice_Bankroll",
				"USB_MickGordon_TheOnlyThingTheyFearIsYou",
				"USB_NEFFEX_Cold",
				"USB_NEFFEX_Rumors",
				"USB_Nerdout_DayAndNight",
				"USB_Ren_HiRen",
				"USB_Ren_SickBoi",
				"USB_Ren_TheTaleOfJennyAndScreech",
				"USB_RichardWagner_RideOfTheValkyries",
				"USB_RickAstley_NeverGonnaGiveYouUp",
				"USB_SubUrban_Cradles",
				"USB_SubUrban_Freak",
				"USB_TheCab_AngelWithAShotgun",
				"USB_PongDance"
			]
		},
		{
			"ClassName": "Playlist_Casper",
			"MaxPriceThreshold": 250,
			"MinPriceThreshold": 250,
			"SellPricePercent": 100,
			"MaxStockThreshold": 3,
			"MinStockThreshold": 1,
			"QuantityPercent": -1,
			"SpawnAttachments": [],
			"Variants": [
				"Playlist_Gamer"
			]
		},
		{
			"ClassName": "MoreUSBsWorldTour_BillyIdol_RebelYell",
			"MaxPriceThreshold": 250,
			"MinPriceThreshold": 250,
			"SellPricePercent": 100,
			"MaxStockThreshold": 3,
			"MinStockThreshold": 1,
			"QuantityPercent": -1,
			"SpawnAttachments": [],
			"Variants": [
				"MoreUSBsWorldTour_BillyTalent_DevilInAMidnightMass",
				"MoreUSBsWorldTour_BillyTalent_FallenLeaves",
				"MoreUSBsWorldTour_Blink182_Dammit",
				"MoreUSBsWorldTour_BrothersOfMetal_RideOfTheValkyries",
				"MoreUSBsWorldTour_Foghat_SlowRide",
				"MoreUSBsWorldTour_Heart_Barracuda",
				"MoreUSBsWorldTour_IronMaiden_TheNumberOfTheBeast",
				"MoreUSBsWorldTour_LosLobos_LaBamba",
				"MoreUSBsWorldTour_LynyrdSkynyrd_SweetHomeAlabama",
				"MoreUSBsWorldTour_REM_TheOneILove",
				"MoreUSBsWorldTour_SteveMillerBand_TheJoker",
				"MoreUSBsWorldTour_StevieRayVaughan_PrideAndJoy",
				"MoreUSBsWorldTour_Sublime_Santeria",
				"MoreUSBsWorldTour_Survivor_EyeOfTheTiger",
				"MoreUSBsWorldTour_TheAllManBrothersBand_RamblinMan",
				"MoreUSBsWorldTour_TheRollingStones_PaintItBlack",
				"MoreUSBsWorldTour_WillieNelson_OnTheRoadAgain"
			]
		},
		{
			"ClassName": "MorePlaylistsWorldTour",
			"MaxPriceThreshold": 250,
			"MinPriceThreshold": 250,
			"SellPricePercent": 100,
			"MaxStockThreshold": 3,
			"MinStockThreshold": 1,
			"QuantityPercent": -1,
			"SpawnAttachments": [],
			"Variants": []
		},
		{
			"ClassName": "MoreUSBs_LeBonLaBruteEtLeTruand",
			"MaxPriceThreshold": 250,
			"MinPriceThreshold": 250,
			"SellPricePercent": 100,
			"MaxStockThreshold": 3,
			"MinStockThreshold": 1,
			"QuantityPercent": -1,
			"SpawnAttachments": [],
			"Variants": [
				"MoreUSBs_Daftpunk_AroundTheWorld",
				"MoreUSBs_Outkast_HeyYa",
				"MoreUSBs_SmashMouth_WhyCantWeBeFriends",
				"MoreUSBs_Katchi_Ofenbach",
				"MoreUSBs_LaCompagnieCreole_CaFaitRireLesOiseaux",
				"MoreUSBs_LinkinPark_InTheEnd",
				"MoreUSBs_Metallica_WhiskeyInTheJar",
				"MoreUSBs_PatWoods_LukyLuke",
				"MoreUSBs_StageLacroix_TeLette",
				"MoreUSBs_TomJones_SexBomb",
				"MoreUSBs_ZZtop_TheGrange",
				"MoreUSBs_ACDC_HighwayToHell",
				"MoreUSBs_BobMarley_DontWorryBeHappy",
				"MoreUSBs_BusterPoindexter_HitTheRoadJack",
				"MoreUSBs_ChuckBerry_JohnnyBGoode",
				"MoreUSBs_CrampeEnMasse_MauditeBoisson",
				"MoreUSBs_DropkickMurphys_Im_ShippingUpToBoston",
				"MoreUSBs_DropkickMurphys_TheStateOfMassachusetts",
				"MoreUSBs_JimmyEatWorld_TheMiddle",
				"MoreUSBs_LaCompagnieCreole_BaMoinEnTiBo",
				"MoreUSBs_NOFX_ChampsElysees",
				"MoreUSBs_Opus_LifeIsLife",
				"MoreUSBs_TheProclaimers_WouldWalk500Miles",
				"MoreUSBs_TotoAfrica",
				"MoreUSBs_UB40_RedRedWine"
			]
		},
		{
			"ClassName": "MorePlaylists",
			"MaxPriceThreshold": 250,
			"MinPriceThreshold": 250,
			"SellPricePercent": 100,
			"MaxStockThreshold": 3,
			"MinStockThreshold": 1,
			"QuantityPercent": -1,
			"SpawnAttachments": [],
			"Variants": []
		},
		{
			"ClassName": "USB_28WeeksLater_ThemeSong",
			"MaxPriceThreshold": 250,
			"MinPriceThreshold": 250,
			"SellPricePercent": 100,
			"MaxStockThreshold": 3,
			"MinStockThreshold": 1,
			"QuantityPercent": -1,
			"SpawnAttachments": [],
			"Variants": [
				"USB_Adele_ChasingPavements",
				"USB_Ahzee_King",
				"USB_AlexClare_TooClose",
				"USB_Alfons_BastaBoi",
				"USB_AliciaKeys_NoOne",
				"USB_AloeBlacc_INeedADollar",
				"USB_Alphabeat_Fascination",
				"USB_AmyMacDonald_MrRockAndRoll",
				"USB_Angerfist_HOAX",
				"USB_Angerfist_Pennywise",
				"USB_Apashe_Annihilation",
				"USB_ATC_AllAroundTheWorld",
				"USB_AudioBullys_ShotYouDown",
				"USB_Avicii_TheNights",
				"USB_AvrilLavigne_Girlfriend",
				"USB_AvrilLavigne_Smile",
				"USB_BackwoodsBadass_BackwoodsBadass",
				"USB_BackwoodsBadass_Killbilly",
				"USB_BackwoodsBadass_LastDance",
				"USB_BackwoodsBadass_RENEGADE",
				"USB_BackwoodsBadass_TellittotheBottle",
				"USB_BackwoodsBadass_WelcometotheWoods",
				"USB_BackwoodsBadass_YuppieFolksCantSurvive",
				"USB_BadMuthaFka_BadMuthaFka",
				"USB_BadMuthaFka_CantFuckwithUs",
				"USB_BadMuthaFka_DownintheHoller",
				"USB_BadMuthaFka_Hillbilly",
				"USB_BadMuthaFka_OldDays",
				"USB_BadMuthaFka_TheOtherWay",
				"USB_BarnsCourtney_GlitterAndGold",
				"USB_Basshunter_NowYourGone",
				"USB_Bassjackers_Derp",
				"USB_Bassjackers_ElMariachi",
				"USB_Beatfreakz_Superfreak",
				"USB_BenNichols_TheLastPaleLightInTheWest",
				"USB_BenNichols_ThisOldDeath",
				"USB_BingCrosby_WinterWonderland",
				"USB_BlackSabbath_Paranoid",
				"USB_blAke_ANewDawn",
				"USB_Blue_CuratinFalls",
				"USB_BounceUnited_Popcorn",
				"USB_BounceUnited_Supernova",
				"USB_BrunoMars_MarryYou",
				"USB_BrunoMars_TheLazySong",
				"USB_ButtholeSurfers_DraculaFromHouston",
				"USB_CallofDutyBlackOps_115",
				"USB_CallofDutyBlackOps_BeautyOfAnnihilation",
				"USB_CalvinHarris_AcceptableInThe80s",
				"USB_CamilleJonesvsFeddeLeGrand_TheCreeps",
				"USB_CaptainJack_BackHome",
				"USB_CaptainJack_Capitano",
				"USB_CaptainJack_CaptainJack",
				"USB_CaptainJack_Centerfold",
				"USB_CaptainJack_DontHaha",
				"USB_CaptainJack_DreamADream",
				"USB_CaptainJack_DrillInstructor",
				"USB_CaptainJack_EinBisschenSpassMussSein",
				"USB_CaptainJack_GetUp",
				"USB_CaptainJack_GiveItUp",
				"USB_CaptainJack_IkoIko",
				"USB_CaptainJack_InTheNavy",
				"USB_CaptainJack_LittleBoy",
				"USB_CaptainJack_SambaBrazil",
				"USB_CaptainJack_SayCaptainSayWot",
				"USB_CaptainJack_SoldierSoldier",
				"USB_CaptainJack_VivaLaVida",
				"USB_CaptainJack_Volare",
				"USB_CaryBrothers_Honestly",
				"USB_Cascada_EverytimeWeTouch",
				"USB_Cascada_TrulyMadlyDeeply",
				"USB_ChiddyBang_RayCharles",
				"USB_ChrisJanson_BuyMeABoat",
				"USB_ChristinaAguilera_Candyman",
				"USB_CitizenCope_Sideways",
				"USB_CodePandorum_Calvaire",
				"USB_ColinHay_BeautifulWorld",
				"USB_ColinHay_MyBrilliantFeat",
				"USB_ColinHay_Overkill",
				"USB_ColterWall_SleepingontheBlacktop",
				"USB_Coolio_GangstasParadiseRemix",
				"USB_CorinneBaileyRae_PutYourRecordsOn",
				"USB_CrazyFrog_AxelFRemix",
				"USB_DaTweekaz_Jgermeister",
				"USB_DavidGuetta_Dangerous",
				"USB_DavidGuetta_LoveIsGone",
				"USB_DavidJordan_SunGoesDown",
				"USB_DayZRapBattle_HerovsBandit",
				"USB_DeanMartin_BabyItsColdOutside",
				"USB_Disney_ASpoonfulOfSugar",
				"USB_Disney_AWholeNewWorld",
				"USB_Disney_BreakingFree",
				"USB_Disney_ChimChimCher_ee",
				"USB_Disney_FriendLikeMe",
				"USB_Disney_HakunaMatata",
				"USB_Disney_IJustCantWaitToBeKing",
				"USB_Disney_IWannaBeLikeYou",
				"USB_Disney_LetItGo",
				"USB_Disney_LetsGoFlyAKite",
				"USB_Disney_OneJumpAhead",
				"USB_Disney_Supercalifragilisticexpialidocious",
				"USB_Disney_TheBareNecessities",
				"USB_Disney_TheWonderfulThingAboutTigers",
				"USB_Disney_UnderTheSea",
				"USB_DJCammy_AnotherDay",
				"USB_DJCammy_AntiRankinCrew",
				"USB_DJCammy_CuppycakevsCelebrateTheSummer",
				"USB_DJCammy_DanceWithMe",
				"USB_DJCammy_DancingInTheDark",
				"USB_DJCammy_DontChaWish",
				"USB_DJCammy_EverlastingLove",
				"USB_DJCammy_EverytimeWeTouch",
				"USB_DJCammy_FieldsofDreams",
				"USB_DJCammy_FluteTune",
				"USB_DJCammy_GirlsJustWannaHaveFun",
				"USB_DJCammy_HardcoreFeelings",
				"USB_DJCammy_HaveYouEver",
				"USB_DJCammy_HereWeCome",
				"USB_DJCammy_Hurricane",
				"USB_DJCammy_ImaRaverBaby",
				"USB_DJCammy_IWishICould",
				"USB_DJCammy_KissKiss",
				"USB_DJCammy_LivingOnAPrayer",
				"USB_DJCammy_LonleyHeart",
				"USB_DJCammy_OnAPartyTrip",
				"USB_DJCammy_PutYourHandsUpInTheAir",
				"USB_DJCammy_SaturdayNite",
				"USB_DJCammy_SexyEyes",
				"USB_DJCammy_ShiningStar",
				"USB_DJCammy_SimplytheBest",
				"USB_DJCammy_StandUpTall",
				"USB_DJCammy_WeAreRavin",
				"USB_DJCammy_WingsOfLove",
				"USB_DJEadesy_DancingInTheDark",
				"USB_DJFlyin_EnergyRush",
				"USB_DJFresh_Gravity",
				"USB_DJFunk_BootyBounce",
				"USB_DJMystick_IDontWannaMissAThing",
				"USB_DJNotgitaclue_AlwaysOnMyMind",
				"USB_DJNotgitaclue_BadBoy",
				"USB_DJNotgitaclue_GetOnUpYourASuperstar",
				"USB_DJNotgitaclue_HeavenAnEarth",
				"USB_DJNotgitaclue_JustMoreBumdiggibum",
				"USB_DJNotgitaclue_LastNight",
				"USB_DJNotgitaclue_OnlyFaceToFace",
				"USB_DJNotgitaclue_PumpinStar",
				"USB_DJNotgitaclue_WellBeFree",
				"USB_DJNotgitaclue_WhoTheFuckIsDJRankin",
				"USB_DJPaulElstak_LuvUmore",
				"USB_DJRankin_AFallingStar",
				"USB_DJRankin_CottonEyedKickinJoe",
				"USB_DJRankin_EveryBreathYouTake",
				"USB_DJRankin_FaceDownAssUp",
				"USB_DJRankin_FreshPrinceOfBelAir",
				"USB_DJRankin_HowCanILove",
				"USB_DJRankin_IAmARaver",
				"USB_DJRankin_IKissYourLips",
				"USB_DJRankin_ImADreamer",
				"USB_DJRankin_KillingMeSoftly",
				"USB_DJRankin_PrettyGreenEyes",
				"USB_DJRankin_RythmIsADancer",
				"USB_DJRankin_StandByMe",
				"USB_DJRankin_SummerOf69",
				"USB_DJRankin_TheClownSong",
				"USB_DJRekkyBee_OverYou",
				"USB_DJSammy_TimeAfterTime",
				"USB_DJSammy_WereinHeaven",
				"USB_DJSkinja_CountryRoads",
				"USB_DJXTC_JustLoseMyLollipop",
				"USB_DJXTC_SweetBluDreemz",
				"USB_DubstepGutter_Demigod",
				"USB_DubstepGutter_GravityFallsTheme",
				"USB_DubstepGutter_ScaryHour",
				"USB_Dubstepia_Hellgate",
				"USB_Duffy_Mercy",
				"USB_Duffy_WarwickAvenue",
				"USB_DVBBS_Pyramids",
				"USB_Eels_FreshFeeling",
				"USB_Elefant_Why",
				"USB_EllieGoulding_AnythingCouldHappen",
				"USB_EmeliSande_MyKindOfLove",
				"USB_EnrigueIglesias_Doyouknow",
				"USB_Estelle_AmericanBoy",
				"USB_EvaCassidyAndKatieMelua_WhatAWonderfulWorld",
				"USB_Everything_Hooch",
				"USB_FabianMazur_Firestarter",
				"USB_FallOutBoy_ThnksfrthMmrs",
				"USB_Feist_1234",
				"USB_FloRida_GDFR",
				"USB_FloRida_Low",
				"USB_FrancisDunnery_GoodLife",
				"USB_FranksChoice",
				"USB_Freefaller_DoThisDoThat",
				"USB_Froto_PiratesoftheCaribbeanRemix",
				"USB_Fun_SightOfTheSun",
				"USB_Fun_SomeNights",
				"USB_Fun_WeAreYoung",
				"USB_Fun_WeOwnedTheNight",
				"USB_FuseODG_DangerousLove",
				"USB_GeorgeEzra_Budapest",
				"USB_GirlsAloud_IThinkWereAloneNow",
				"USB_GnarlsBarkley_SmileyFaces",
				"USB_GoodnightTexas_TheRailroad",
				"USB_Gorillaz_19_2000",
				"USB_Gorillaz_19_2000Remix",
				"USB_Gorillaz_AllAlone",
				"USB_Gorillaz_ClintEastwood",
				"USB_Gorillaz_ClintEastwoodRemix",
				"USB_Gorillaz_Dare",
				"USB_Gorillaz_DemonDays",
				"USB_Gorillaz_DirtyHarry",
				"USB_Gorillaz_DontGetLostInHeaven",
				"USB_Gorillaz_DoubleBass",
				"USB_Gorillaz_ElManana",
				"USB_Gorillaz_EveryPlanetWeReachIsDead",
				"USB_Gorillaz_FeelGoodInc",
				"USB_Gorillaz_FireComingOutOfTheMonkeysHead",
				"USB_Gorillaz_FiveFour",
				"USB_Gorillaz_KidsWithGuns",
				"USB_Gorillaz_LastLivingSouls",
				"USB_Gorillaz_LatinSimone",
				"USB_Gorillaz_M1A1",
				"USB_Gorillaz_ManResearch",
				"USB_Gorillaz_NewGenious",
				"USB_Gorillaz_NovemberHasCome",
				"USB_Gorillaz_OGreenWorld",
				"USB_Gorillaz_Punk",
				"USB_Gorillaz_Re_Hash",
				"USB_Gorillaz_RocktheHouse",
				"USB_Gorillaz_SlowCountry",
				"USB_Gorillaz_SoundCheck",
				"USB_Gorillaz_Starshine",
				"USB_Gorillaz_TomorrowComesToday",
				"USB_Gorillaz_WhiteLight",
				"USB_Gotye_SomebodyThatIUsedToKnow",
				"USB_GraceKelly_Mika",
				"USB_GuidedByVoices_HoldOnHope",
				"USB_GwenStefani_WindItUp",
				"USB_GymClassHeroes_CupidsChokehold",
				"USB_HankWilliams_AloneAndForsaken",
				"USB_HankWilliams_CountryHeroes",
				"USB_HappyHardcore_AltonTowersTheme",
				"USB_HappyHardcore_ISawAnAngel",
				"USB_HappyHardcore_RushHour",
				"USB_HappyHardcore_ShootingStar",
				"USB_Helion_GoodVibes",
				"USB_Helion_Joker",
				"USB_HollywoodUndead_EverywhereIGo",
				"USB_Hozier_InTheWoodsSomewhere",
				"USB_IggyAzalea_Fancy",
				"USB_InfinityInk_Infinity",
				"USB_JaceEverett_BadThings",
				"USB_JackJohnson_GoodPeople",
				"USB_Jamelia_BewareOfTheDog",
				"USB_JamesBay_HoldBacktheRiver",
				"USB_JamieNCommons_LeadMeHome",
				"USB_JamieT_CalmDownDearest",
				"USB_JasonMraz_IWontGiveUp",
				"USB_Jem_They",
				"USB_JeremyKay_HaveItAll",
				"USB_JohnCale_Hallelujah",
				"USB_JohnCarpenter_HalloweenTheme",
				"USB_JohnnyCash_AintNoGrave",
				"USB_JosephArthur_IntheSun",
				"USB_JoshRadin_Winter",
				"USB_JunkieKidAndBL3R_HardHouse",
				"USB_JustJack_StarzInTheirEyes",
				"USB_KaiserChiefs_EverydayILoveYouLessAndLess",
				"USB_KaiserChiefs_Ruby",
				"USB_KanyeWest_Homecoming",
				"USB_KanyeWest_Stronger",
				"USB_KateNash_Foundations",
				"USB_KellyClarkson_HeartbeatSong",
				"USB_KO_TimeInABottleRemix",
				"USB_KylieMinogue_IBelieveInYou",
				"USB_Labrinth_BeneathYourBeautiful",
				"USB_Labrinth_ExpressYourself",
				"USB_LazloBane_Superman",
				"USB_Lemar_ItsNotThatEasy",
				"USB_LeonaLewis_BleedingLove",
				"USB_LeonJackson_WhenYouBelieve",
				"USB_Leroy_GoodTime",
				"USB_LilNasX_OldTownRoadRemix",
				"USB_LilyAllen_Alfie",
				"USB_LilyAllen_LDN",
				"USB_LMFAO_SexyAndIKnowIt",
				"USB_Ludacris_MoveBitch",
				"USB_LunchMoneyLewis_Bills",
				"USB_MajorLazer_LeanOn",
				"USB_ManuChao_MeGustasTu",
				"USB_MarkRonson_UptownFunk",
				"USB_MarkRonson_Valerie",
				"USB_Maroon5_MovesLikeJagger",
				"USB_Maroon5_OneMoreNight",
				"USB_Maroon5_Sugar",
				"USB_MartinGarrix_Animals",
				"USB_MartinSexton_Diner",
				"USB_MassiveAttack_Teardrop",
				"USB_Maximes_SummerJam",
				"USB_McFly_AllAboutYou",
				"USB_McFly_Obviously",
				"USB_MeghanTrainor_DearFutureHusband",
				"USB_Mika_BigGirl",
				"USB_Mika_HappyEnding",
				"USB_Mika_LoveToday",
				"USB_Mika_Relax",
				"USB_MikeEmilio_Clown",
				"USB_MikeOldfield_TubularBells",
				"USB_MrBassBoost_Engage",
				"USB_Niche_ItsAllAboutTheMoney",
				"USB_Nickelback_Rockstar",
				"USB_Nickleback_Photograph",
				"USB_NickNolan_LifeofSin",
				"USB_NilLara_FightingForMyLove",
				"USB_NinaSimone_IPutASpellOnYou",
				"USB_Nizlopi_JCBSong",
				"USB_Ohmie_AsocialSociopath",
				"USB_Ohmie_BleedingToDeath",
				"USB_OllyMurs_Busy",
				"USB_OllyMurs_DanceWithMeTonight",
				"USB_OneDirection_LiveWhileWereYoung",
				"USB_OneDirection_WhatMakesYouBeautiful",
				"USB_PhilCollins_InTheAirTonight",
				"USB_PlainWhiteTs_HeyThereDelilah",
				"USB_PSY_GangnamStyle",
				"USB_RhettMiller_OurLove",
				"USB_Rihanna_DontStopTheMusic",
				"USB_RizzleKicks_MamaDoTheHump",
				"USB_RobbieWilliams_Candy",
				"USB_RobbieWilliams_Radio",
				"USB_Robyn_BeMine",
				"USB_Rockwell_SomebodysWatchingMe",
				"USB_RonanKeating_FatherAndSon",
				"USB_Rudimental_FeelTheLove",
				"USB_SaintLouisSymphonyOrchestra_OFortuna",
				"USB_SamSmith_StayWithMe",
				"USB_SamTinnesz_FarFromHome",
				"USB_ScoutingForGirls_ElvisAintDead",
				"USB_ScoutingForGirls_Heartbeat",
				"USB_ScoutingForGirls_ShesSoLovely",
				"USB_SeamusHaji_LastNightADJSavedMyLife",
				"USB_SeanKingston_BeautifulGirls",
				"USB_SeSa_LikeThisLikeThat",
				"USB_ShawnJames_ThroughtheValley",
				"USB_ShawnMullins_AllInMyHead",
				"USB_Sigma_Higher",
				"USB_SimonWebbe_ComingAroundAgain",
				"USB_SkanAndKrale_NoGlory",
				"USB_Skrillex_Kyoto",
				"USB_Slipknot_Duality",
				"USB_SwedishHouseMafia_DontYouWorryChild",
				"USB_SwedishHouseMafia_Greyhound",
				"USB_T2_Heartbroken",
				"USB_TakeThat_Shine",
				"USB_TammanyHall_Cindy",
				"USB_TaylorSwift_WeAreNeverEverGettingBackTogether",
				"USB_TeamGeo_Friendly",
				"USB_TeamGeo_IWantAnAK",
				"USB_TeamGeo_IWantSomeBeans",
				"USB_TeamGeo_PlayDayZ",
				"USB_Teknova_IevanPolkkaRemix",
				"USB_TheBlackEyedPeas_JustCantGetEnough",
				"USB_TheChemicalBrothers_Galvanize",
				"USB_TheCitizensofHalloween_ThisIsHalloween",
				"USB_TheCoral_DreamingofYou",
				"USB_TheHoosiers_CopsAndRobbers",
				"USB_TheHoosiers_GoodbyeMrA",
				"USB_TheHoosiers_WorriedAboutRay",
				"USB_TheLionKing_HakunaMatataRemix",
				"USB_TheMavericks_IWantToKnow",
				"USB_TheOrdinaryBoys_BoysWillBeBoys",
				"USB_TheOrdinaryBoys_ILuvU",
				"USB_ThePolyphonicSpree_LightAndDay",
				"USB_TheSaturdays_Notorious",
				"USB_TheShins_NewSlang",
				"USB_TheSpecials_GhostTown",
				"USB_TheTingTings_ThatsNotMyName",
				"USB_TheVamps_SomebodyToYou",
				"USB_TheWanted_ChasingTheSun",
				"USB_TheWhiteBuffalo_ComeJoinTheMurder",
				"USB_TheWhiteBuffalo_HouseoftheRisingSun",
				"USB_TheWhiteStripes_SevenNationArmyRemix",
				"USB_TomMac_Half",
				"USB_Toto_AfricaRemix",
				"USB_Train_DriveBy",
				"USB_TrapMusicNow_ThePurgeAnnouncement",
				"USB_TrapWarrior_ReadyOrNot",
				"USB_Ultrabeat_IGoCrazy",
				"USB_Ultrabeat_PrettyGreenEyes",
				"USB_Underoath_WritingOnTheWalls",
				"USB_Underworld_BornSlippy",
				"USB_UnitingNations_OutOfTouch",
				"USB_Vairo_Bohica",
				"USB_Vairo_Flawless",
				"USB_Vairo_HideAndSeek",
				"USB_Vairo_Manchineel",
				"USB_Vairo_Nightmare",
				"USB_Vairo_PocoLoco",
				"USB_Vairo_Raindance",
				"USB_Vairo_Scarab",
				"USB_Vairo_Storm",
				"USB_Vairo_Swara",
				"USB_Vairo_Vinterleken",
				"USB_Voodevil_HideAndSeek",
				"USB_WarrenZevon_WerewolvesOfLondon",
				"USB_Weezer_BeverleyHills",
				"USB_WillSparks_ROMA",
				"USB_WizKhalifa_SeeYouAgain",
				"USB_Xillions_SomebodyLikeMe",
				"USB_XTM_FlyOnTheWingsOfLove",
				"USB_Yellowcard_OceanAvenue"
			]
		},
		{
			"ClassName": "Playlist_KillswitchEngage_DisarmTheDescent",
			"MaxPriceThreshold": 250,
			"MinPriceThreshold": 250,
			"SellPricePercent": 100,
			"MaxStockThreshold": 3,
			"MinStockThreshold": 1,
			"QuantityPercent": -1,
			"SpawnAttachments": [],
			"Variants": [
				"Playlist_FRSP2_BackwoodsBadass",
				"Playlist_FRSP2_BadMuthaFka",
				"Playlist_FRSP2_CaptainJack",
				"Playlist_FRSP2_Disney",
				"Playlist_FRSP2_DJCammy",
				"Playlist_FRSP2_DJNotgitaclue",
				"Playlist_FRSP2_DJRankin",
				"Playlist_FRSP2_Gorillaz",
				"Playlist_FRSP2_TeamGeo",
				"Playlist_FRSP2_Vairo"
			]
		},
		{
			"ClassName": "USB_ArminVanBuuren_BlahBlahBlah",
			"MaxPriceThreshold": 250,
			"MinPriceThreshold": 250,
			"SellPricePercent": 100,
			"MaxStockThreshold": 3,
			"MinStockThreshold": 1,
			"QuantityPercent": -1,
			"SpawnAttachments": [],
			"Variants": [
				"USB_DenisLeary_ImAnAsshole",
				"USB_Blake_DayZGoBy",
				"USB_BadLipReading_Seagulls",
				"USB_SJFW_DumbWaysToDieInDayZ",
				"USB_TheOdd1sOut_LifeIsFun",
				"USB_RaCostelloe_OpenRoad",
				"USB_LilRevive_666",
				"USB_LilRevive_FridayThe13th",
				"USB_LilRevive_MySoulToTake",
				"USB_LilRevive_RunningWithTheDevil",
				"USB_LilRevive_TellTheReaperImSorry",
				"USB_DJNassim_DZSummerMix2023",
				"USB_DVBBS_Tsunami",
				"USB_FloRida_MyHouse",
				"USB_FloRida_RightRound_HBzHardBounceRemix",
				"USB_Jibbs_ChainHangLowCrizzly_AFKRemix",
				"USB_LewisCapaldi_SomeoneYouLoved_PaulGannonRemix",
				"USB_KickTheHabit_NeverSatisfied",
				"USB_EDubble_BeAKing",
				"USB_VybzKartel_Popcaan_WeNeverFearDem",
				"USB_CollieBuddz_ComeAround",
				"USB_BonnieTyler_INeedAHero",
				"USB_MiracleOfSound_ValhallaCalling",
				"USB_LeagueOfLegends_Rise",
				"USB_RascalFlatts_LifeIsAHighwayJesseBlochBootleg",
				"USB_Enter_Sandman_Remastered",
				"USB_JAYZ_Empire_State_Of_Mind",
				"USB_ModernWarfareIII_ZombiesOSTDamned6",
				"USB_TheCranberries_Zombie",
				"USB_Wonderwall_Remastered",
				"USB_Zentryc_Levitation",
				"USB_NatteVisstick_Cumshot",
				"USB_NatteVisstick_VisstickAnthemP1",
				"USB_NatteVisstick_FuckingDoorweekteTeringVisstickUitDeMagnetronVanJeOma",
				"USB_HCTM_Sudno",
				"USB_SP4CKS_MakeMeFeelLike",
				"USB_Anor_ThePerfectGirl",
				"USB_Cenker_LetMeGo",
				"USB_Yarimov_Controlla",
				"USB_Silencee_TheWayYouDoIt",
				"USB_Agony_Avi",
				"USB_DIKKEBAAP_ITripIt",
				"USB_NatteVisstick_DeutscheTechnoBunker",
				"USB_Nalim_RPG",
				"USB_GhostfacePlaya_DeadOne",
				"USB_Scriptonite_Noframes",
				"USB_Indablack_TikTok",
				"USB_Scriptonite_Rejoice",
				"USB_Kizaru_Bandana",
				"USB_Pablo_AllStars",
				"USB_Markul_Serpentine",
				"USB_MiyagiNAndyPanda_Marmalade",
				"USB_MiyagiNAndyPanda_Yamakasi",
				"USB_Pharaoh_Freestyle",
				"USB_Pharaoh_Smart",
				"USB_Pharaoh_WildForExample",
				"USB_Biv_FranksLicensePlate",
				"USB_Biv_SkipMe",
				"USB_Biv_System",
				"USB_Biv_WeProbablyShouldntTalkAnymore",
				"USB_Fukkit_Basher",
				"USB_Fukkit_LasOvejasMueren",
				"USB_Jenx2_OopsAllStraps",
				"USB_SavageGasp_GhostInTheShell",
				"USB_WarlordColossus_DontFightSkeletons",
				"USB_WarlordColossus_RedemptionsHereAtLast",
				"USB_WarlordColossus_Warslugz",
				"USB_Zari_Comedown",
				"USB_MacMiller_WatchingMovies",
				"USB_MacMiller_Loud",
				"USB_MacMiller_SmileBack",
				"USB_MacMiller_SelfCare",
				"USB_MacMiller_TheSpins",
				"USB_RiffRaff_HowToBeTheMan",
				"USB_RiffRaff_TipToe3",
				"USB_RiffRaff_DolceNGabbana",
				"USB_ENXK_HYPERDRIVE",
				"USB_ENXK_ETERNAL",
				"USB_Ghost_Track_01",
				"USB_Ghost_Track_02",
				"USB_Kesha_TiKToK",
				"USB_WuTangClan_BringDaRuckus",
				"USB_WuTangClan_CREAM",
				"USB_WuTangClan_ClanInDaFront",
				"USB_WuTangClan_GravelPit",
				"USB_WuTangClan_ProtectYaNeck",
				"USB_WuTangClan_Tearz",
				"USB_WuTangClan_WuTang7thChamber",
				"USB_WuTangClan_WuTang7thChamberPt2",
				"USB_WuTangClan_WuTangClanAintNuthingTaFWit",
				"USB_Capela_Track_01",
				"USB_Capela_Track_02",
				"USB_Capela_Track_03",
				"USB_Capela_Track_04",
				"USB_Capela_Track_05",
				"USB_Capela_Track_06",
				"USB_Capela_Track_07",
				"USB_Capela_Track_08",
				"USB_Capela_Track_09",
				"USB_Capela_Track_10",
				"USB_ACDC_HighWayToHell",
				"USB_Adolfeen_PartyVDome",
				"USB_Casablanca_TheGirlOfLucifer",
				"USB_CicoBandReneRendy_Piatocek",
				"USB_CrystalCastle_Kerosene",
				"USB_ELPRESIDENTO_TESTOSTERON",
				"USB_Eptic_Payback",
				"USB_Gothminister_Star",
				"USB_JAX_Intro",
				"USB_JAX_MariaSalvador",
				"USB_JAX_OstiaLido",
				"USB_Kabat_Corrida",
				"USB_KarelZich_MasChutMajoranky",
				"USB_KRUCIPUSK_Mamanek",
				"USB_LIMMA_ScrapsOfMemory",
				"USB_LondonBoys_ImGonnaGiveMyHeart",
				"USB_MaximTurbulence_JedeJedeMasinka",
				"USB_MercedesBenzFan_BabyMyBabyDontCry",
				"USB_MiyagiAndyPanda_Freeman",
				"USB_Neries_10Minut",
				"USB_Netsky_IRefuse",
				"USB_OzzyOsbourne_PatientNumber9",
				"USB_PinotelloNLilTexas_Spongebob",
				"USB_Separ_Sunset",
				"USB_Slen_SleepSeason",
				"USB_SodomaGomora_ChovejteSeTuJakoSoDoma",
				"USB_SOILWORK_Stalfagel",
				"USB_SubmatikANDDualistic_LetMeFeel",
				"USB_ViktorSheen_WHO",
				"USB_Vojtaano_BudulinekVSGalantniJelen",
				"USB_Wardruna_Lyfjaberg",
				"USB_ABBA_DancingQueen",
				"USB_ACDC_BackInBlack",
				"USB_ACDC_HighwayToHell",
				"USB_Akinyele_PutItInYourMouth",
				"USB_Alesana_Apology",
				"USB_AliceDeejay_BetterOffAlone",
				"USB_AmandaPerez_GodSendMeAnAngel",
				"USB_AmericanParatrooper_BloodOnTheRivers",
				"USB_AndrewGold_SpookyScarySkeletons",
				"USB_Apashe_GoodNews",
				"USB_Apashe_Majesty",
				"USB_BarryMcGuire_EveOfDestruction",
				"USB_BeastieBoys_BrassMonkey",
				"USB_BeastieBoys_FightforYourRight",
				"USB_BeastieBoys_Girls",
				"USB_BeastieBoys_PaulRevere",
				"USB_BeastieBoys_SlowAndLow",
				"USB_BeastieBoys_SlowRide",
				"USB_BendingRealityToHoistTheColors",
				"USB_Benefit_WarpToWorld69",
				"USB_BillieEilish_BadGuy",
				"USB_BillieEilish_BuryAFriend",
				"USB_BillieEilish_WhenThePartysOver",
				"USB_BinaryFinary_1999",
				"USB_BlackEyedPeas_WhereIsTheLove",
				"USB_blessthefall_HollowBodies",
				"USB_Blondie_Atomic",
				"USB_BlueOysterCult_TheReaper",
				"USB_BluesSaraceno_DogsOfWar",
				"USB_BluesSaraceno_GraveDigger",
				"USB_BluesSaraceno_TheBibleOrTheGun",
				"USB_BluesSaraceno_TheRiver",
				"USB_BlueSwede_HookedOnAFeeling",
				"USB_BobbyMcFerrin_DontWorryBeHappy",
				"USB_BobMarley_BuffaloSoldier",
				"USB_BobMarley_EverythingsGonnaBeAllRight",
				"USB_BobMarley_GetUpStandUp",
				"USB_BobMarley_IsThisLove",
				"USB_BobMarley_NaturalMystic",
				"USB_BobMarley_NoWomanNoCry",
				"USB_BobMarley_OneLove",
				"USB_BobMarley_RedemptionSong",
				"USB_BobRossRemixed_HappyLittleClouds",
				"USB_BoBurnham_WelcomeToTheInternet",
				"USB_BomfunkMC_Freestyler",
				"USB_BringMeTheHorizon_ChelseaSmile",
				"USB_BringMeTheHorizon_PrayforPlagues",
				"USB_BrotherDege_TooOldToDieYoung",
				"USB_CaliforniaDreamin",
				"USB_CarlDouglas_KungFuFighting",
				"USB_CatStevens_WildWorld",
				"USB_Cazzette_SheWantsMeDead",
				"USB_ChrisLeDoux_ThisCowboysHat",
				"USB_CitizenSoldier_Deathbed",
				"USB_ComeWithMe_SpecialD",
				"USB_CosmicGate_Firewire",
				"USB_CreedenceClearwaterRevival_BadMoonRising",
				"USB_CreedenceClearwaterRevival_FortunateSon",
				"USB_CreedenceClearwaterRevival_HaveYouEverSeenTheRain",
				"USB_CyndiLauper_TimeAfterTime",
				"USB_CyndiLauper_TrueColours",
				"USB_DaftPunk_HarderBetterFasterStronger",
				"USB_DaHool_MeetHerAtTheLoveparade",
				"USB_DanBull_DayZFastRap",
				"USB_DaveMcCullen_RaveHeaven",
				"USB_DawnWall_DevilsNight",
				"USB_DawnWall_Fears",
				"USB_DawnWall_ISeeU",
				"USB_DawnWall_IShouldHaveBeenThere",
				"USB_DawnWall_Judgement",
				"USB_DawnWall_MohicanSun",
				"USB_DawnWall_NeverSay",
				"USB_DawnWall_RainGod",
				"USB_deadmau5_BridgedByALightwave",
				"USB_deadmau5_GhostsNStuff",
				"USB_deadmau5_LetGo",
				"USB_deadmau5_Polaris",
				"USB_deadmau5_WhenTheSummerDies",
				"USB_DeanMartin_AintThatAKickInTheHead",
				"USB_DizzieRascal_Bonkers",
				"USB_DizzieRascal_Dream",
				"USB_DizzieRascal_Girls",
				"USB_DizzieRascal_ILoveYou",
				"USB_DizzieRascal_Jezebel",
				"USB_DizzieRascal_WannaBe",
				"USB_DJHixxy_Discoland",
				"USB_DJHixxy_ISeeTheLight",
				"USB_DJQuicksilver_Bellisima",
				"USB_DJSammy_ForeverYoung",
				"USB_DJTiesto_Ayla",
				"USB_DragonForce_ThroughTheFireAndFlames",
				"USB_DrunkenMaster_TheScallywag",
				"USB_DubstepGutter_FrEliseRemix",
				"USB_DubstepGutter_RickAndMorty",
				"USB_Dumbo_PinkElephantsOnParadeRemix",
				"USB_Ehde_PlanetPurge",
				"USB_Eiffel65_Blue",
				"USB_ElectricSix_DangerHighVoltage",
				"USB_ElectricSix_GayBar",
				"USB_EnterShikari_SorryYoureNotAWinner",
				"USB_Ephixa_LosingYou",
				"USB_Europe_TheFinalCountdown",
				"USB_EvilBongMovieIntroSong",
				"USB_FabianMazurSnavs_Arena",
				"USB_FallOutBoy_Centuries",
				"USB_Feint_Vagrant",
				"USB_Feint_Words",
				"USB_FrankSinatra_ComeFlyWithMe",
				"USB_GaelicStorm_Scalliwag",
				"USB_Get_Well_Soon",
				"USB_GunsNRoses_WelcomeToTheJungle",
				"USB_GuruJoshProject_Infinity2008",
				"USB_Hoobastank_CrawlingInTheDark",
				"USB_Horse_Race",
				"USB_IanVanDahl_CastlesInTheSky",
				"USB_IniKamoze_HereComestheHotstepper",
				"USB_IsraelIZKamakawiwoole_SomewhereOvertheRainbow",
				"USB_JenTitus_ODeath",
				"USB_JimCarrey_SomebodyToLove",
				"USB_JimCroce_TimeInABottle",
				"USB_Journey_DontStopBelievin",
				"USB_JustinCross_DrinkTheWater",
				"USB_Kaleo_BrokenBones",
				"USB_KateBush_RunningUpThatHill",
				"USB_KevinAndPerry_FollowMe",
				"USB_KevinBloodyWilson_DarlinImSoHorny",
				"USB_Korn_FreakOnaLeash",
				"USB_LesleyGore_YouDontOwnMe",
				"USB_LimpBizkit_Boiler",
				"USB_LinkinPark_NewDivide",
				"USB_Logic_1_800_273_8255",
				"USB_LornaShore_SunEater",
				"USB_LostWoodsDubstepRemix_Ephixa",
				"USB_Lum_YoungMan",
				"USB_M83_MidnightCity",
				"USB_MamaCass_DreamALittleDreamOfMe",
				"USB_MarilynMonroe_IWannaBeLovedByYou",
				"USB_MarinaAndTheDiamonds_Lies",
				"USB_MarlonCraft_AtTheDoor",
				"USB_MarlonCraft_Brainiacs",
				"USB_MarlonCraft_Break",
				"USB_MarlonCraft_CantCallIt",
				"USB_MarlonCraft_CockyHumble",
				"USB_MarlonCraft_DearLife",
				"USB_MarlonCraft_Family",
				"USB_MarlonCraft_GangShit",
				"USB_MarlonCraft_GetOffMyYard",
				"USB_MarlonCraft_Grateful",
				"USB_MarlonCraft_HoodieWeather",
				"USB_MarlonCraft_InTheEnd",
				"USB_MarlonCraft_JuliusRandle",
				"USB_MarlonCraft_LookinUp",
				"USB_MarlonCraft_LotToGive",
				"USB_MarlonCraft_Loyal",
				"USB_MarlonCraft_MomsWhiskey",
				"USB_MarlonCraft_NotEverybody",
				"USB_MarlonCraft_OffBeat",
				"USB_MarlonCraft_Roadtrippin",
				"USB_MarlonCraft_TellMeToday",
				"USB_MarlonCraft_TheHappy",
				"USB_MarlonCraft_TheWorkinMan",
				"USB_MarlonCraft_WhereIAm",
				"USB_MarlonCraft_Wherever",
				"USB_MarlonCraft_WorldChamp",
				"USB_Marnik_UpAndDown",
				"USB_MaskedWarrior66_DevouredByTheUnknown",
				"USB_MaskedWarrior66_BoogeyMan",
				"USB_MaskedWarrior66_TrapDrift",
				"USB_Maximes_ITouchMyself",
				"USB_MCSparky_Maximes",
				"USB_MetalGearSolidV_TheManWhoSoldTheWorld",
				"USB_MichaelJackson_ManInTheMirror",
				"USB_MichealJackson_BeatIt",
				"USB_MichealJackson_BillyJean",
				"USB_MichealJackson_BlackAndWhite",
				"USB_MichealJackson_DontStopTillGetEnough",
				"USB_MichealJackson_HumanNature",
				"USB_MichealJackson_IWannaRockWithYou",
				"USB_MichealJackson_SmoothCriminal",
				"USB_MichealJackson_TheWayYouMakeMeFeel",
				"USB_MichealJackson_Thriller",
				"USB_Millencolin_NoCigar",
				"USB_MissMayI_HeyMister",
				"USB_Miyagi_IGotLove",
				"USB_Miyagi_Marlboro",
				"USB_MoonshineBandits_PassMeTheAmmo",
				"USB_MrOizo_FlatBeat",
				"USB_Nakatomi_ChildrenOfTheNight",
				"USB_NancySinatra_BangBang",
				"USB_NancySinatra_TheseBootsAreMadeForWalkin",
				"USB_Nas_ICan",
				"USB_Nightcore_FinalCountdownRemix",
				"USB_Nightcore_TheFuckingShow",
				"USB_Nikkita_Poltergeist",
				"USB_NineOneOne_ImABadMan",
				"USB_OneRepublic_RescueMe",
				"USB_Otherwise_Soldiers",
				"USB_OZone_NumaNumaRemix",
				"USB_PapaRoach_BetweenAngelsAndInsects",
				"USB_Pendulum_BloodSugar",
				"USB_Pendulum_Watercolour",
				"USB_POD_Alive",
				"USB_polkkabouncemix",
				"USB_Prince_PurpleRain",
				"USB_Prodigy_Firestarter",
				"USB_Prodigy_VoodooPeople",
				"USB_Queen_AnotherOneBitesTheDust",
				"USB_Queen_BohemianRhapsody",
				"USB_Queen_IWantItAll",
				"USB_Queen_IWantToBreakFree",
				"USB_Queen_KeepYourselfAlive",
				"USB_Queen_RadioGaGa",
				"USB_Queen_WeAreTheChampions",
				"USB_Queen_WeWillRockYou",
				"USB_Raffi_BananaPhone",
				"USB_Rammstein_Adieu",
				"USB_Rammstein_Angst",
				"USB_Rammstein_DickeTitten",
				"USB_Rammstein_IchWill",
				"USB_Rammstein_Sonne",
				"USB_Redbone_ComeAndGetYourLove",
				"USB_RedHotChiliPeppers_Californication",
				"USB_RedHotChiliPeppers_ScarTissue",
				"USB_RKelly_IBelieveICanFly",
				"USB_RKelly_TheWorldsGreatest",
				"USB_RUFUS_Innerbloom",
				"USB_Ryllz_Nemesis",
				"USB_SaintClue_ComeAlive",
				"USB_SandervanDoorn_MartinGarrix_DVBBS_GoldSkies",
				"USB_Scooter_Fire",
				"USB_Scooter_ImRaving",
				"USB_Scooter_JumpinAllOverTheWorld",
				"USB_Scooter_Kalinka",
				"USB_Scooter_Maria",
				"USB_Scooter_Nessaja",
				"USB_Scooter_Posse",
				"USB_Scooter_TheLogicalSong",
				"USB_ScotlandTheBrave",
				"USB_ScottBrown_Ultrabeat_Elysium",
				"USB_September_CryForYou",
				"USB_SkattBros_LifeAtTheOutpost",
				"USB_SmashMouth_AllStar",
				"USB_SoSolidCrew_21Seconds",
				"USB_StephenLynch_DungeonsAndDragons",
				"USB_StephenLynch_IrishPub",
				"USB_StephenLynch_SpecialFred",
				"USB_StephenLynch_UglyBaby",
				"USB_StephenLynch_VanillaIceCream",
				"USB_StephenLynch_VoicesInMyHead",
				"USB_StephenLynch_YouCaughtMeSpankingIt",
				"USB_Stonebank_RippedToPieces",
				"USB_Stonebank_Stronger",
				"USB_SuicideSilence_WakeUp",
				"USB_SystemOfADown_Aerials",
				"USB_SystemOfADown_Toxicity",
				"USB_Tamia_CarelessWhisper",
				"USB_Tatu_30Minutes",
				"USB_Tatu_AllAboutUs",
				"USB_Tatu_AllTheThingsSheSaid",
				"USB_Tatu_HowSoonIsNow",
				"USB_Tatu_NotGonnaGetUs",
				"USB_Technohead_IWannaBeAHippy",
				"USB_TenaciousD_DoubleTeam",
				"USB_TenaciousD_FuckHerGently",
				"USB_TenaciousD_Tribute",
				"USB_tetristhemetrapremix",
				"USB_TheBeatles_Help",
				"USB_TheBeatles_IWannaHoldYourHand",
				"USB_TheBeatles_SoHappyTogether",
				"USB_TheBeatles_Yesterday",
				"USB_TheDeadSouth_InHellIllBeInGoodCompany",
				"USB_TheDeadSouth_PeopleAreStrange",
				"USB_TheFatRat_Monody",
				"USB_TheFugees_ReadyOrNot",
				"USB_TheInkSpots_IDontWantToSetTheWorldOnFire",
				"USB_TheRollingStones_PaintItBlack",
				"USB_TheRollingStones_SympathyForTheDevil",
				"USB_TheSteelWoods_LetTheRainComeDown",
				"USB_TheSugarhillGang_Apache",
				"USB_TheSugarhillGang_RappersDelight",
				"USB_TheWeedSong",
				"USB_TheXX_Intro",
				"USB_ThomasBenjaminWildEsq_AlwaysLookOnTheBrightSideOfLife",
				"USB_ThomasBenjaminWildEsq_EverythingStopsForTea",
				"USB_ThomasBenjaminWildEsq_IGotItFromAgnes",
				"USB_ThomasBenjaminWildEsq_ImJustHereForTheSwearing",
				"USB_ThomasBenjaminWildEsq_IveNoMoreFsToGive_ElectricTimebombRemix",
				"USB_ThomasBenjaminWildEsq_IveNoMoreFucksToGive",
				"USB_ThomasBenjaminWildEsq_LetsGetReadyToTurnItOn",
				"USB_ThomasBenjaminWildEsq_MagazinePages",
				"USB_ThomasBenjaminWildEsq_OhSocialMedia",
				"USB_ThomasBenjaminWildEsq_OoDeLally",
				"USB_ThomasBenjaminWildEsq_PantsDrunk",
				"USB_ThomasBenjaminWildEsq_StopBeingAnArsehole",
				"USB_ThomasBenjaminWildEsq_TheBareNecessities",
				"USB_ThomasBenjaminWildEsq_WellThisIsShit",
				"USB_TJH87_GoodLife",
				"USB_TomJones_ItsNotUnusual",
				"USB_TomNovyCatDealers_YourBody",
				"USB_Toto_HoldTheLine",
				"USB_TRex_BangAGongGetItOn",
				"USB_Tupac_AllEyezonMe",
				"USB_Tupac_BrokenWings",
				"USB_Tupac_CaliforniaLove",
				"USB_Tupac_DearMama",
				"USB_Tupac_GhettoGospel",
				"USB_Tupac_HitEmUp",
				"USB_Tupac_ShortyWannaBeaThug",
				"USB_TVThemes_AltonTowers",
				"USB_TVThemes_BennyHill",
				"USB_TVThemes_BobTheBuilder",
				"USB_TVThemes_Cheers",
				"USB_TVThemes_DuckTails",
				"USB_TVThemes_FreshPrinceOfBelAir",
				"USB_TVThemes_GhostBusters",
				"USB_TVThemes_HappyDays",
				"USB_TVThemes_MASH",
				"USB_TVThemes_OompaLoompaSongs",
				"USB_TVThemes_SuperMarioBrothers",
				"USB_TVThemes_ThePinkPanther",
				"USB_TVThemes_WinnieThePooh",
				"USB_Twista_Sunshine",
				"USB_UB40_Groovin",
				"USB_UB40_HereIAm",
				"USB_UB40_ICantHelpFallingInLovewithYou",
				"USB_UB40_IGotYouBabe",
				"USB_UB40_KingstonTown",
				"USB_UB40_RedRedWine",
				"USB_UB40_TearsFromMyEyes",
				"USB_UB40_WayYouDoTheThingsYouDo",
				"USB_UB40_YourABeautifulWoman",
				"USB_Vagina",
				"USB_VanillaIce_IceIceBaby",
				"USB_VanillaIce_NinjaRap",
				"USB_VeraLynn_WellMeetAgain",
				"USB_VIDAQUESEGUE_BettyBoop",
				"USB_Vigiland_FridayNight",
				"USB_WheelerWalkerJr_DropEmOut",
				"USB_WheelerWalkerJr_FamilyTree",
				"USB_WindsNocturne",
				"USB_WoolyBully",
				"USB_ZagerEvans_InTheYear2525"
			]
		},
		{
			"ClassName": "Playlist_FRSP1_BeastieBoys",
			"MaxPriceThreshold": 250,
			"MinPriceThreshold": 250,
			"SellPricePercent": 100,
			"MaxStockThreshold": 3,
			"MinStockThreshold": 1,
			"QuantityPercent": -1,
			"SpawnAttachments": [],
			"Variants": [
				"USB_LilRevive",
				"Playlist_FRSP1_BobMarley",
				"Playlist_FRSP1_DawnWall",
				"Playlist_FRSP1_deadmau5",
				"Playlist_FRSP1_DizzieRascal",
				"Playlist_FRSP1_MarlonCraft",
				"Playlist_FRSP1_MichaelJackson",
				"Playlist_FRSP1_Queen",
				"Playlist_FRSP1_Rammstein",
				"Playlist_FRSP1_Scooter",
				"Playlist_FRSP1_StephenLynch",
				"Playlist_FRSP1_Tatu",
				"Playlist_FRSP1_TheBeatles",
				"Playlist_FRSP1_ThomasBenjaminWildEsq",
				"Playlist_FRSP1_Tupac",
				"Playlist_FRSP1_TVThemes",
				"Playlist_FRSP1_UB40",
				"Playlist_Capela",
				"Playlist_WuTangClan",
				"Playlist_Breazy_01",
				"Playlist_Breazy_02",
				"Playlist_Breazy_03"
			]
		},
		{
			"ClassName": "USB_GTA_V_FlyLoFM",
			"MaxPriceThreshold": 500,
			"MinPriceThreshold": 500,
			"SellPricePercent": 100,
			"MaxStockThreshold": 3,
			"MinStockThreshold": 1,
			"QuantityPercent": -1,
			"SpawnAttachments": [],
			"Variants": [
				"USB_GTA_V_SoulwaxFM",
				"USB_GTA_VC_Emotion_98_3",
				"USB_GTA_VC_Fever_105",
				"USB_GTA_VC_FlashFM",
				"USB_GTA_VC_VRock",
				"USB_GTA_VC_Wave_103",
				"USB_GTA_SA_KRose",
				"USB_GTA_SA_KDST",
				"USB_GTA_SA_RadioLosSantos",
				"USB_GTA_SA_SFUR"
			]
		},
		{
			"ClassName": "USB_AdamSandler_TheChristmasSong",
			"MaxPriceThreshold": 250,
			"MinPriceThreshold": 250,
			"SellPricePercent": 100,
			"MaxStockThreshold": 3,
			"MinStockThreshold": 1,
			"QuantityPercent": -1,
			"SpawnAttachments": [],
			"Variants": [
				"USB_BingCrosby_WinterWonderland",
				"USB_BobRivers_WhatIfEminemDidJingleBells",
				"USB_BrendaLee_RockinAroundTheChristmasTree",
				"USB_BuddyBrown_RedneckJingleBells",
				"USB_DanCollins_IllBeStonedForChristmas",
				"USB_DeanMartin_AMarshmallowWorld",
				"USB_DeanMartin_LetItSnowLetItSnowLetItSnow",
				"USB_DougieMacLean_AuldLangSyne",
				"USB_FrankSinatra_ChristmasWaltz",
				"USB_FrankSinatra_SantaClausIsComingToTown",
				"USB_FrankSinatra_SilentNight",
				"USB_FrankieLaine_AND_JoStafford_ChristmasRoses",
				"USB_GeneAutry_FrostytheSnowman",
				"USB_JimReeves_AnOldChristmasCard",
				"USB_KidsfromtheHeart_TheAngelsSang",
				"USB_MargaretWhiting_ChristmasCandy",
				"USB_MargaretWhiting_TheMistletoeKiss",
				"USB_PorkyPig_BlueChristmas",
				"USB_SethMacFarlane_LittleJackFrostGetLost",
				"USB_SpikeJones_ImGettinNothinForChristmas",
				"USB_TenaciousD_The12DrugsofChristmas",
				"USB_TheAndrewsSisters_Jing_a_LingJing_a_Ling",
				"USB_TheRonettes_SleighRide",
				"USB_WillLyle_JingleBells"
			]
		},
		{
			"ClassName": "Playlist_Christmas",
			"MaxPriceThreshold": 500,
			"MinPriceThreshold": 500,
			"SellPricePercent": 100,
			"MaxStockThreshold": 3,
			"MinStockThreshold": 1,
			"QuantityPercent": -1,
			"SpawnAttachments": [],
			"Variants": []
		},
		{
			"ClassName": "USB_DubFX_BoyWithLuv",
			"MaxPriceThreshold": 250,
			"MinPriceThreshold": 250,
			"SellPricePercent": 100,
			"MaxStockThreshold": 3,
			"MinStockThreshold": 1,
			"QuantityPercent": -1,
			"SpawnAttachments": [],
			"Variants": [
				"USB_DubFX_EvenFlow",
				"USB_DubFX_FlyWithMe",
				"USB_DubFX_FutureReflections",
				"USB_DubFX_Intensions",
				"USB_DubFX_LoveSomeone",
				"USB_DubFX_Madness",
				"USB_DubFX_NothingElseMatters",
				"USB_DubFX_SocietyGates",
				"USB_DubFX_SootheYourPain",
				"USB_DubFX_StepOnMyTrip",
				"USB_DubFX_TheRainIsGone",
				"USB_DubFX_TimeWillTell",
				"USB_DubFX_WanderingLove",
				"USB_TheEminemShow_Track_01",
				"USB_TheEminemShow_Track_02",
				"USB_TheEminemShow_Track_03",
				"USB_TheEminemShow_Track_04",
				"USB_TheEminemShow_Track_05",
				"USB_TheEminemShow_Track_06",
				"USB_TheEminemShow_Track_07",
				"USB_TheEminemShow_Track_08",
				"USB_TheEminemShow_Track_09",
				"USB_TheEminemShow_Track_10",
				"USB_TheEminemShow_Track_11",
				"USB_TheEminemShow_Track_12",
				"USB_TheEminemShow_Track_13",
				"USB_TheEminemShow_Track_14",
				"USB_TheEminemShow_Track_15",
				"USB_TheEminemShow_Track_16",
				"USB_TheEminemShow_Track_17",
				"USB_TheEminemShow_Track_18",
				"USB_TheEminemShow_Track_19",
				"USB_TheEminemShow_Track_20"
			]
		},
		{
			"ClassName": "USB_1990s_GreatestHits",
			"MaxPriceThreshold": 500,
			"MinPriceThreshold": 500,
			"SellPricePercent": 100,
			"MaxStockThreshold": 3,
			"MinStockThreshold": 1,
			"QuantityPercent": -1,
			"SpawnAttachments": [],
			"Variants": [
				"USB_CelineDion_GreatestHits",
				"USB_DMX_GreatestHits",
				"USB_ElvisPresley_GreatestHits",
				"USB_Evanescense_GreatestHits",
				"USB_Tupac_GreatestHits",
				"USB_FRSP1_DubFX",
				"USB_TheEminemShow"
			]
		}
	]
}