{
    "m_Version": 5,
    "EnableStatusTab": 1,
    "EnablePartyTab": 1,
    "EnableServerInfoTab": 1,
    "EnableServerRulesTab": 1,
    "EnableTerritoryTab": 1,
    "EnableBookMenu": 1,
    "CreateBookmarks": 0,
    "ShowHaBStats": 1,
    "ShowPlayerFaction": 0,
    "RuleCategories": [
        {
            "CategoryName": "General",
            "Rules": [
                {
                    "RuleParagraph": "1.1.",
                    "RuleText": "Politische, Rassistische und persönliche Beleidigungen sind nicht erlaubt."
                },
                {
                    "RuleParagraph": "1.2.",
                    "RuleText": "Cheating/Bugabusing ist nicht erlaubt."
                },
                {
                    "RuleParagraph": "1.3.",
                    "RuleText": "Seid fair zu einander, ein gemütliches Umgangs-Klima ist gewünscht."
                },
                {
                    "RuleParagraph": "1.4.",
                    "RuleText": "Glitching, Duping und Ausnutzung von Spielmechaniken sind verboten!"
                },
                {
                    "RuleParagraph": "1.5.",
                    "RuleText": "Wenn der Spieler durch einen Zombie, ein Tier oder eigenes Spielverhalten stirbt, erlischt das Recht auf das Spielerinventar."
                },
				{
                    "RuleParagraph": "1.6.",
                    "RuleText": "Dauer Parken am Trader ist nicht erlaubt, nutzt Eure Basis"
                },
				{
                    "RuleParagraph": "1.6.",
                    "RuleText": "Keine Basen innerhalb von 500m von einer Militäreinrichtung."
                },
				{
                    "RuleParagraph": "1.6.",
                    "RuleText": "Nur Basen mit Flagpole und Flagge gelten als Basis. Der Besitzer hat darauf zu achten, das die Fahne immer gehisst ist."
                },
				{
                    "RuleParagraph": "1.6.",
                    "RuleText": "Die Benutzung von Autos und Helis erfolgt auf eigene Gefahr. Wenn es einen Fehler auf dem Server gibt, der nicht vom Benutzer verschuldet ist, kann der Admin helfen. Um für den Verlust eines Fahrzeugs entschädigt zu werden, muss Videomaterial zur Verfügung gestellt werden."
                },
				{
                    "RuleParagraph": "1.6.",
                    "RuleText": "Nur Basen mit Flagpole und Flagge gelten als Basis. Der Besitzer hat darauf zu achten, das die Fahne immer gehisst ist."
                }
            ]
        }
    ],
    "DisplayServerSettingsInServerInfoTab": 1,
    "SettingCategories": [
        {
            "CategoryName": "Base-Building Settings",
            "Settings": [
                {
                    "SettingTitle": "Expansion.Settings.BaseBuilding.CanCraftVanillaBasebuilding",
                    "SettingText": "",
                    "SettingValue": ""
                },
                {
                    "SettingTitle": "Expansion.Settings.BaseBuilding.CanCraftExpansionBasebuilding",
                    "SettingText": "",
                    "SettingValue": ""
                }
            ]
        },
        {
            "CategoryName": "Raid Settings",
            "Settings": [
                {
                    "SettingTitle": "Expansion.Settings.Raid.CanRaidSafes",
                    "SettingText": "",
                    "SettingValue": ""
                },
                {
                    "SettingTitle": "Expansion.Settings.Raid.SafeExplosionDamageMultiplier",
                    "SettingText": "",
                    "SettingValue": ""
                },
                {
                    "SettingTitle": "Expansion.Settings.Raid.SafeProjectileDamageMultiplier",
                    "SettingText": "",
                    "SettingValue": ""
                },
                {
                    "SettingTitle": "Expansion.Settings.Raid.ExplosionTime",
                    "SettingText": "",
                    "SettingValue": ""
                },
                {
                    "SettingTitle": "Expansion.Settings.Raid.ExplosionDamageMultiplier",
                    "SettingText": "",
                    "SettingValue": ""
                },
                {
                    "SettingTitle": "Expansion.Settings.Raid.ProjectileDamageMultiplier",
                    "SettingText": "",
                    "SettingValue": ""
                }
            ]
        },
        {
            "CategoryName": "Territory Settings",
            "Settings": [
                {
                    "SettingTitle": "Expansion.Settings.Territory.TerritorySize",
                    "SettingText": "",
                    "SettingValue": ""
                },
                {
                    "SettingTitle": "Expansion.Settings.Territory.UseWholeMapForInviteList",
                    "SettingText": "",
                    "SettingValue": ""
                }
            ]
        },
        {
            "CategoryName": "Map Settings",
            "Settings": [
                {
                    "SettingTitle": "Expansion.Settings.Map.NeedGPSItemForKeyBinding",
                    "SettingText": "",
                    "SettingValue": ""
                },
                {
                    "SettingTitle": "Expansion.Settings.Map.NeedMapItemForKeyBinding",
                    "SettingText": "",
                    "SettingValue": ""
                }
            ]
        },
        {
            "CategoryName": "Party Settings",
            "Settings": [
                {
                    "SettingTitle": "Expansion.Settings.Party.MaxMembersInParty",
                    "SettingText": "",
                    "SettingValue": ""
                },
                {
                    "SettingTitle": "Expansion.Settings.Party.UseWholeMapForInviteList",
                    "SettingText": "",
                    "SettingValue": ""
                }
            ]
        }
    ],
    "Links": [
        {
            "Name": "Homepage",
            "URL": "https://www.gamblerpack.de",
            "IconName": "Homepage",
            "IconColor": -14473430
        },
        {
            "Name": "Feedback",
            "URL": "https://discord.com/channels/1294067503382925322/1294327558547968072",
            "IconName": "Forums",
            "IconColor": -14473430
        },
        {
            "Name": "Discord",
            "URL": "https://discord.gg/JV2dCSKWws",
            "IconName": "Discord",
            "IconColor": -9270822
        },
        {
            "Name": "Steam Gruppe",
            "URL": "https://steamcommunity.com/groups/gamblerpack",
            "IconName": "Steam",
            "IconColor": -14006434
        },
        {
            "Name": "GitHub DasBrunzel",
            "URL": "https://github.com/DasBrunzel/no0bz-DayZ-Deerisle-Server",
            "IconName": "GitHub",
            "IconColor": -16777216
        },
        {
            "Name": "YouTube",
            "URL": "https://www.youtube.com/c/GamblerPack",
            "IconName": "YouTube",
            "IconColor": -65536
        }
    ],
    "Descriptions": [
        {
            "CategoryName": "Generelle Regeln",
            "Descriptions": [
                {
                    "DescriptionText": ""
                },
                {
                    "DescriptionText": ""
                },
                {
                    "DescriptionText": ""
                },
				{
                    "DescriptionText": ""
                },
				{
                    "DescriptionText": ""
                },
				{
                    "DescriptionText": ""
                },
				{
                    "DescriptionText": ""
                },
				{
                    "DescriptionText": ""
                },
				{
                    "DescriptionText": ""
                },
				{
                    "DescriptionText": ""
                }
            ]
        },
        {
            "CategoryName": "Mod Info",
            "Descriptions": [
                {
                    "DescriptionText": "Lorem ipsum dolor sit amet, consetetur sadipscing elitr, sed diam nonumy eirmod tempor invidunt ut labore et dolore magna aliquyam erat, sed diam voluptua. At vero eos et accusam et justo duo dolores et ea rebum. Stet clita kasd gubergren, no sea takimata sanctus est Lorem ipsum dolor sit amet. Lorem ipsum dolor sit amet, consetetur sadipscing elitr, sed diam nonumy eirmod tempor invidunt ut labore et dolore magna aliquyam erat, sed diam voluptua. At vero eos et accusam et justo duo dolores et ea rebum. Stet clita kasd gubergren, no sea takimata sanctus est Lorem ipsum dolor sit amet."
                },
                {
                    "DescriptionText": "Lorem ipsum dolor sit amet, consetetur sadipscing elitr, sed diam nonumy eirmod tempor invidunt ut labore et dolore magna aliquyam erat, sed diam voluptua. At vero eos et accusam et justo duo dolores et ea rebum. Stet clita kasd gubergren, no sea takimata sanctus est Lorem ipsum dolor sit amet. Lorem ipsum dolor sit amet, consetetur sadipscing elitr, sed diam nonumy eirmod tempor invidunt ut labore et dolore magna aliquyam erat, sed diam voluptua. At vero eos et accusam et justo duo dolores et ea rebum. Stet clita kasd gubergren, no sea takimata sanctus est Lorem ipsum dolor sit amet."
                },
                {
                    "DescriptionText": "Lorem ipsum dolor sit amet, consetetur sadipscing elitr, sed diam nonumy eirmod tempor invidunt ut labore et dolore magna aliquyam erat, sed diam voluptua. At vero eos et accusam et justo duo dolores et ea rebum. Stet clita kasd gubergren, no sea takimata sanctus est Lorem ipsum dolor sit amet. Lorem ipsum dolor sit amet, consetetur sadipscing elitr, sed diam nonumy eirmod tempor invidunt ut labore et dolore magna aliquyam erat, sed diam voluptua. At vero eos et accusam et justo duo dolores et ea rebum. Stet clita kasd gubergren, no sea takimata sanctus est Lorem ipsum dolor sit amet."
                }
            ]
        }
    ],
    "CraftingCategories": [
        {
            "CategoryName": "Accessories",
            "Results": [
                "armband_",
                "armband_white",
                "eyepatch_improvised"
            ]
        },
        {
            "CategoryName": "Backpacks",
            "Results": [
                "courierbag",
                "furcourierbag",
                "furimprovisedbag",
                "improvisedbag",
                "leathersack_brown"
            ]
        },
        {
            "CategoryName": "Base-Building",
            "Results": [
                "expansionbarbedwirekit",
                "fencekit",
                "expansionfloorkit",
                "expansionhelipadkit",
                "expansionhescokit",
                "expansionrampkit",
                "shelterkit",
                "expansionstairkit",
                "territoryflagkit",
                "expansionwallkit",
                "watchtowerkit"
            ]
        },
        {
            "CategoryName": "Camouflage",
            "Results": [
                "camonet",
                "ghillieatt_tan",
                "ghillieatt_mossy",
                "ghillieatt_woodland",
                "ghilliebushrag_tan",
                "ghilliebushrag_mossy",
                "ghilliebushrag_woodland",
                "ghilliehood_tan",
                "ghilliehood_mossy",
                "ghilliehood_woodland",
                "ghilliesuit_tan",
                "ghilliesuit_mossy",
                "ghilliesuit_woodland",
                "ghillietop_tan",
                "ghillietop_mossy",
                "ghillietop_woodland"
            ]
        },
        {
            "CategoryName": "Cooking",
            "Results": [
                "fireplace",
                "firewood",
                "handdrillkit"
            ]
        },
        {
            "CategoryName": "Fishing",
            "Results": [
                "bait",
                "bonebait",
                "bonehook",
                "improvisedfishingrod"
            ]
        },
        {
            "CategoryName": "Food",
            "Results": [
                "carpfilletmeat",
                "mackerelfilletmeat",
                "expansionmilkbottle",
                "potato",
                "slicedpumpkin"
            ]
        },
        {
            "CategoryName": "Horticulture",
            "Results": [
                "pepperseeds",
                "pumpkinseeds",
                "tomatoseeds",
                "zucchiniseeds"
            ]
        },
        {
            "CategoryName": "Lights",
            "Results": [
                "longtorch",
                "torch"
            ]
        },
        {
            "CategoryName": "Medical Supplies",
            "Results": [
                "bloodbagiv",
                "salinebagiv",
                "splint"
            ]
        },
        {
            "CategoryName": "Melee Weapons",
            "Results": [
                "nailedbaseballbat",
                "stoneknife"
            ]
        },
        {
            "CategoryName": "Storage",
            "Results": [
                "woodencrate"
            ]
        },
        {
            "CategoryName": "Supplies",
            "Results": [
                "boarpelt",
                "burlapsack",
                "burlapstrip",
                "longwoodenstick",
                "expansionlumber1",
                "expansionlumber1_5",
                "expansionlumber3",
                "nails",
                "netting",
                "rag",
                "rope",
                "sharpwoodenstick",
                "smallstone",
                "tannedleather",
                "woodenplank",
                "woodenstick"
            ]
        },
        {
            "CategoryName": "Weapon Modifications",
            "Results": [
                "sawedoffizh18shotgun"
            ]
        },
        {
            "CategoryName": "Weapon Attachments",
            "Results": [
                "improvisedsuppressor"
            ]
        }
    ],
    "EnableCraftingRecipesTab": 1
}